setup.py
bingaudistributionsRonaldoCD/Binomialdistribution.py
bingaudistributionsRonaldoCD/Gaussiandistribution.py
bingaudistributionsRonaldoCD/Generaldistribution.py
bingaudistributionsRonaldoCD/__init__.py
bingaudistributionsRonaldoCD.egg-info/PKG-INFO
bingaudistributionsRonaldoCD.egg-info/SOURCES.txt
bingaudistributionsRonaldoCD.egg-info/dependency_links.txt
bingaudistributionsRonaldoCD.egg-info/not-zip-safe
bingaudistributionsRonaldoCD.egg-info/top_level.txt