Metadata-Version: 1.0
Name: bingaudistributionsRonaldoCD
Version: 1.0
Summary: Gaussian and Binomial distributions
Home-page: UNKNOWN
Author: Ronaldo Cachi
Author-email: w.ronaldo.cd@gmail.com
License: UNKNOWN
Platform: UNKNOWN
